[
  {
    "full_name": "scalar/scalar",
    "stargazers_count": 7676,
    "open_issues_count": 187,
    "forks_count": 242
  },
  {
    "full_name": "trurl-master/jsdom-testing-mocks",
    "stargazers_count": 116,
    "open_issues_count": 4,
    "forks_count": 7
  },
  {
    "full_name": "nodejs/build",
    "stargazers_count": 506,
    "open_issues_count": 107,
    "forks_count": 167
  },
  {
    "full_name": "libuv/libuv",
    "stargazers_count": 24426,
    "open_issues_count": 188,
    "forks_count": 3608
  },
  {
    "full_name": "llvm/llvm-project",
    "stargazers_count": 29405,
    "open_issues_count": 27357,
    "forks_count": 12150
  },
  {
    "full_name": "shadcn-ui/ui",
    "stargazers_count": 75844,
    "open_issues_count": 1330,
    "forks_count": 4764
  },
  {
    "full_name": "kelvinmwinuka/cognito-next",
    "stargazers_count": 29,
    "open_issues_count": 0,
    "forks_count": 7
  },
  {
    "full_name": "piranha/twinspark-js",
    "stargazers_count": 422,
    "open_issues_count": 1,
    "forks_count": 20
  },
  {
    "full_name": "maslianok/react-resize-detector",
    "stargazers_count": 1259,
    "open_issues_count": 0,
    "forks_count": 91
  },
  {
    "full_name": "itajaja/url-matcher",
    "stargazers_count": 17,
    "open_issues_count": 0,
    "forks_count": 1
  },
  {
    "full_name": "Danziger/slotjs",
    "stargazers_count": 273,
    "open_issues_count": 4,
    "forks_count": 94
  },
  {
    "full_name": "johakr/html5-slot-machine",
    "stargazers_count": 477,
    "open_issues_count": 5,
    "forks_count": 240
  },
  {
    "full_name": "nextauthjs/next-auth",
    "stargazers_count": 25107,
    "open_issues_count": 404,
    "forks_count": 3553
  },
  {
    "full_name": "clinicjs/node-clinic",
    "stargazers_count": 5695,
    "open_issues_count": 103,
    "forks_count": 125
  },
  {
    "full_name": "facebook/docusaurus",
    "stargazers_count": 56982,
    "open_issues_count": 338,
    "forks_count": 8580
  },
  {
    "full_name": "trpc/trpc",
    "stargazers_count": 35167,
    "open_issues_count": 127,
    "forks_count": 1263
  },
  {
    "full_name": "asteasolutions/zod-to-openapi",
    "stargazers_count": 997,
    "open_issues_count": 24,
    "forks_count": 61
  },
  {
    "full_name": "lukemorales/exhaustive",
    "stargazers_count": 339,
    "open_issues_count": 0,
    "forks_count": 5
  },
  {
    "full_name": "AlexSugak/barebones",
    "stargazers_count": 14,
    "open_issues_count": 0,
    "forks_count": 4
  },
  {
    "full_name": "tailwindlabs/headlessui",
    "stargazers_count": 26300,
    "open_issues_count": 92,
    "forks_count": 1085
  },
  {
    "full_name": "webdriverio/recorder-extension",
    "stargazers_count": 10,
    "open_issues_count": 2,
    "forks_count": 4
  },
  {
    "full_name": "ngneat/falso",
    "stargazers_count": 3220,
    "open_issues_count": 16,
    "forks_count": 120
  },
  {
    "full_name": "tc39/ecma262",
    "stargazers_count": 15084,
    "open_issues_count": 462,
    "forks_count": 1285
  },
  {
    "full_name": "TanStack/query",
    "stargazers_count": 42764,
    "open_issues_count": 95,
    "forks_count": 2926
  },
  {
    "full_name": "pmndrs/zustand",
    "stargazers_count": 48371,
    "open_issues_count": 5,
    "forks_count": 1500
  },
  {
    "full_name": "pmndrs/jotai",
    "stargazers_count": 18865,
    "open_issues_count": 6,
    "forks_count": 623
  },
  {
    "full_name": "savkaoleg/react-form-sample",
    "stargazers_count": 1,
    "open_issues_count": 0,
    "forks_count": 0
  },
  {
    "full_name": "savkaoleg/react-recoil-bmi-calculator",
    "stargazers_count": 1,
    "open_issues_count": 0,
    "forks_count": 0
  },
  {
    "full_name": "savkaoleg/multifarm",
    "stargazers_count": 1,
    "open_issues_count": 0,
    "forks_count": 0
  },
  {
    "full_name": "jaredpalmer/razzle",
    "stargazers_count": 11109,
    "open_issues_count": 137,
    "forks_count": 866
  }
]